{
    "room_id": "3PDFU",
    "creator_id": "p_6a465c5aa98db",
    "game": {
        "deck": [],
        "discard_pile": [],
        "players": [
            {
                "id": "p_6a465c5aa98db",
                "name": "dancogg",
                "is_bot": false,
                "cards": [],
                "called_uno": false
            },
            {
                "id": "p_6a4688faf3e90",
                "name": "AndinyGG",
                "is_bot": false,
                "cards": [],
                "called_uno": false
            }
        ],
        "current_turn": 0,
        "direction": 1,
        "selected_color": null,
        "status": "lobby",
        "winner_id": null,
        "logs": [
            "Game room returned to lobby."
        ],
        "last_action_time": 1783008135.985975,
        "has_drawn_this_turn": false,
        "accumulated_draw_penalty": 0,
        "initial_card_count": 10,
        "last_play_cards": []
    }
}